CHANGELOG.md
LICENSE
dynaconf_aws_loader/__init__.py
dynaconf_aws_loader/loader.py
dynaconf_aws_loader/util.py
dynaconf_aws_loader-0.5.0.dist-info/LICENSE
dynaconf_aws_loader-0.5.0.dist-info/METADATA
dynaconf_aws_loader-0.5.0.dist-info/WHEEL
dynaconf_aws_loader-0.5.0.dist-info/RECORD
