Metadata-Version: 2.1
Name: dynaconf-aws-loader
Version: 0.5.0
Summary: A custom loader for Dynaconf that uses AWS Systems Manager Parameter Store as a source of truth.
Home-page: https://github.com/fictivekin/dynaconf-aws-loader
License: MIT
Keywords: dynaconf,AWS,SSM
Author: Joël Perras
Author-email: joel@fictivekin.com
Requires-Python: >=3.8,<4.0
Classifier: Environment :: Console
Classifier: License :: OSI Approved :: MIT License
Classifier: Operating System :: OS Independent
Classifier: Programming Language :: Python :: 3
Classifier: Programming Language :: Python :: 3.8
Classifier: Programming Language :: Python :: 3.9
Classifier: Programming Language :: Python :: 3.10
Classifier: Programming Language :: Python :: 3.11
Classifier: Topic :: Software Development :: Documentation
Classifier: Topic :: Software Development :: Libraries :: Python Modules
Requires-Dist: boto3 (>=1.26,<2.0)
Requires-Dist: botocore (>=1.29,<2.0)
Requires-Dist: dynaconf (>=3.1,<4.0)
Project-URL: Repository, https://github.com/fictivekin/dynaconf-aws-loader
